buscacep.py
python_cep-0.4.1.dist-info/LICENSE
python_cep-0.4.1.dist-info/METADATA
python_cep-0.4.1.dist-info/WHEEL
python_cep-0.4.1.dist-info/top_level.txt
python_cep-0.4.1.dist-info/RECORD
